[
  {
    "date": "2024-03-20",
    "close": 503.6824951172,
    "volume": 11711100
  },
  {
    "date": "2024-03-21",
    "close": 505.9143676758,
    "volume": 9712500
  },
  {
    "date": "2024-03-22",
    "close": 507.727722168,
    "volume": 8117000
  },
  {
    "date": "2024-03-25",
    "close": 501.1915893555,
    "volume": 8380600
  },
  {
    "date": "2024-03-26",
    "close": 494.0875244141,
    "volume": 11205400
  },
  {
    "date": "2024-03-27",
    "close": 492.0648803711,
    "volume": 9989700
  },
  {
    "date": "2024-03-28",
    "close": 483.8149719238,
    "volume": 15212800
  },
  {
    "date": "2024-04-01",
    "close": 489.5639953613,
    "volume": 9247000
  },
  {
    "date": "2024-04-02",
    "close": 495.5621337891,
    "volume": 11081000
  },
  {
    "date": "2024-04-03",
    "close": 504.8980712891,
    "volume": 12099200
  },
  {
    "date": "2024-04-04",
    "close": 509.0628967285,
    "volume": 26476300
  },
  {
    "date": "2024-04-05",
    "close": 525.4232177734,
    "volume": 19242000
  },
  {
    "date": "2024-04-08",
    "close": 517.3626098633,
    "volume": 13260600
  },
  {
    "date": "2024-04-09",
    "close": 515.0211181641,
    "volume": 10881400
  },
  {
    "date": "2024-04-10",
    "close": 517.940612793,
    "volume": 11418500
  },
  {
    "date": "2024-04-11",
    "close": 521.2584228516,
    "volume": 10369500
  },
  {
    "date": "2024-04-12",
    "close": 510.0393066406,
    "volume": 11944900
  },
  {
    "date": "2024-04-15",
    "close": 498.4117736816,
    "volume": 13512900
  },
  {
    "date": "2024-04-16",
    "close": 497.9434204102,
    "volume": 9847900
  },
  {
    "date": "2024-04-17",
    "close": 492.3737792969,
    "volume": 12193700
  },
  {
    "date": "2024-04-18",
    "close": 499.9760131836,
    "volume": 14808700
  },
  {
    "date": "2024-04-19",
    "close": 479.3213806152,
    "volume": 25111000
  },
  {
    "date": "2024-04-22",
    "close": 479.9789733887,
    "volume": 17271100
  },
  {
    "date": "2024-04-23",
    "close": 494.2967529297,
    "volume": 15079200
  },
  {
    "date": "2024-04-24",
    "close": 491.7061767578,
    "volume": 37772700
  },
  {
    "date": "2024-04-25",
    "close": 439.7756347656,
    "volume": 82890700
  },
  {
    "date": "2024-04-26",
    "close": 441.6787414551,
    "volume": 32691400
  },
  {
    "date": "2024-04-29",
    "close": 431.047454834,
    "volume": 21502600
  },
  {
    "date": "2024-04-30",
    "close": 428.6064147949,
    "volume": 18429500
  },
  {
    "date": "2024-05-01",
    "close": 437.5936279297,
    "volume": 20344900
  },
  {
    "date": "2024-05-02",
    "close": 440.0745544434,
    "volume": 15221300
  },
  {
    "date": "2024-05-03",
    "close": 450.3171691895,
    "volume": 16489100
  },
  {
    "date": "2024-05-06",
    "close": 463.9873046875,
    "volume": 15094600
  },
  {
    "date": "2024-05-07",
    "close": 466.5380249023,
    "volume": 13406800
  },
  {
    "date": "2024-05-08",
    "close": 470.8822021484,
    "volume": 11683900
  },
  {
    "date": "2024-05-09",
    "close": 473.6919250488,
    "volume": 9437700
  },
  {
    "date": "2024-05-10",
    "close": 474.4690856934,
    "volume": 10750000
  },
  {
    "date": "2024-05-13",
    "close": 466.3088684082,
    "volume": 14668800
  },
  {
    "date": "2024-05-14",
    "close": 470.1348876953,
    "volume": 10478600
  },
  {
    "date": "2024-05-15",
    "close": 479.7897033691,
    "volume": 13100500
  },
  {
    "date": "2024-05-16",
    "close": 471.5098571777,
    "volume": 16608200
  },
  {
    "date": "2024-05-17",
    "close": 470.1947021484,
    "volume": 10807300
  },
  {
    "date": "2024-05-20",
    "close": 467.1358337402,
    "volume": 11745100
  },
  {
    "date": "2024-05-21",
    "close": 462.9411315918,
    "volume": 11742200
  },
  {
    "date": "2024-05-22",
    "close": 466.0796813965,
    "volume": 10078600
  },
  {
    "date": "2024-05-23",
    "close": 464.0869750977,
    "volume": 11747900
  },
  {
    "date": "2024-05-24",
    "close": 476.4817199707,
    "volume": 12012300
  },
  {
    "date": "2024-05-28",
    "close": 478.175567627,
    "volume": 10175800
  },
  {
    "date": "2024-05-29",
    "close": 472.6357116699,
    "volume": 9226200
  },
  {
    "date": "2024-05-30",
    "close": 465.3523254395,
    "volume": 10735200
  },
  {
    "date": "2024-05-31",
    "close": 465.1331481934,
    "volume": 16919800
  },
  {
    "date": "2024-06-03",
    "close": 475.7543640137,
    "volume": 11279400
  },
  {
    "date": "2024-06-04",
    "close": 475.2561950684,
    "volume": 7088700
  },
  {
    "date": "2024-06-05",
    "close": 493.2605285645,
    "volume": 15690500
  },
  {
    "date": "2024-06-06",
    "close": 491.9652709961,
    "volume": 10667300
  },
  {
    "date": "2024-06-07",
    "close": 491.1681518555,
    "volume": 9380700
  },
  {
    "date": "2024-06-10",
    "close": 500.7731323242,
    "volume": 11236900
  },
  {
    "date": "2024-06-11",
    "close": 505.6254272461,
    "volume": 9673700
  },
  {
    "date": "2024-06-12",
    "close": 506.9904174805,
    "volume": 11983200
  },
  {
    "date": "2024-06-13",
    "close": 502.2677001953,
    "volume": 9954600
  },
  {
    "date": "2024-06-14",
    "close": 502.8262023926,
    "volume": 10243300
  },
  {
    "date": "2024-06-17",
    "close": 505.2896728516,
    "volume": 11266600
  },
  {
    "date": "2024-06-18",
    "close": 498.1685180664,
    "volume": 13060400
  },
  {
    "date": "2024-06-20",
    "close": 500.3727111816,
    "volume": 11801200
  },
  {
    "date": "2024-06-21",
    "close": 493.4710083008,
    "volume": 23130700
  },
  {
    "date": "2024-06-24",
    "close": 497.5900878906,
    "volume": 13525300
  },
  {
    "date": "2024-06-25",
    "close": 509.2491760254,
    "volume": 12109800
  },
  {
    "date": "2024-06-26",
    "close": 511.7624511719,
    "volume": 8882300
  },
  {
    "date": "2024-06-27",
    "close": 518.1854248047,
    "volume": 10121200
  },
  {
    "date": "2024-06-28",
    "close": 502.8860168457,
    "volume": 15855100
  },
  {
    "date": "2024-07-01",
    "close": 503.3447875977,
    "volume": 10328200
  },
  {
    "date": "2024-07-02",
    "close": 508.1520690918,
    "volume": 7739500
  },
  {
    "date": "2024-07-03",
    "close": 508.6108398438,
    "volume": 6005600
  },
  {
    "date": "2024-07-05",
    "close": 538.4815063477,
    "volume": 21354100
  },
  {
    "date": "2024-07-08",
    "close": 527.9196166992,
    "volume": 14917500
  },
  {
    "date": "2024-07-09",
    "close": 528.5978393555,
    "volume": 8753200
  },
  {
    "date": "2024-07-10",
    "close": 533.275390625,
    "volume": 10983300
  },
  {
    "date": "2024-07-11",
    "close": 511.3436279297,
    "volume": 16458300
  },
  {
    "date": "2024-07-12",
    "close": 497.5501708984,
    "volume": 19750500
  },
  {
    "date": "2024-07-15",
    "close": 494.8473510742,
    "volume": 12539200
  },
  {
    "date": "2024-07-16",
    "close": 488.4942321777,
    "volume": 14075800
  },
  {
    "date": "2024-07-17",
    "close": 460.7677307129,
    "volume": 28076600
  },
  {
    "date": "2024-07-18",
    "close": 474.5910949707,
    "volume": 19267200
  },
  {
    "date": "2024-07-19",
    "close": 475.5286254883,
    "volume": 15149400
  },
  {
    "date": "2024-07-22",
    "close": 486.110534668,
    "volume": 12023100
  },
  {
    "date": "2024-07-23",
    "close": 487.3971252441,
    "volume": 9455500
  },
  {
    "date": "2024-07-24",
    "close": 460.0496520996,
    "volume": 17649700
  },
  {
    "date": "2024-07-25",
    "close": 452.2104492188,
    "volume": 18240500
  },
  {
    "date": "2024-07-26",
    "close": 464.4679870605,
    "volume": 14222400
  },
  {
    "date": "2024-07-29",
    "close": 464.4779052734,
    "volume": 11339600
  },
  {
    "date": "2024-07-30",
    "close": 461.9645996094,
    "volume": 11390400
  },
  {
    "date": "2024-07-31",
    "close": 473.5737915039,
    "volume": 24285800
  },
  {
    "date": "2024-08-01",
    "close": 496.4231872559,
    "volume": 43083100
  },
  {
    "date": "2024-08-02",
    "close": 486.8485717773,
    "volume": 24044700
  },
  {
    "date": "2024-08-05",
    "close": 474.4714355469,
    "volume": 21396200
  },
  {
    "date": "2024-08-06",
    "close": 492.7828063965,
    "volume": 20955000
  },
  {
    "date": "2024-08-07",
    "close": 487.6265563965,
    "volume": 20105300
  },
  {
    "date": "2024-08-08",
    "close": 508.2817382812,
    "volume": 16156800
  },
  {
    "date": "2024-08-09",
    "close": 516.4002685547,
    "volume": 13696600
  },
  {
    "date": "2024-08-12",
    "close": 514.5850219727,
    "volume": 9767400
  },
  {
    "date": "2024-08-13",
    "close": 527.1417236328,
    "volume": 13743800
  },
  {
    "date": "2024-08-14",
    "close": 525.366394043,
    "volume": 11444200
  },
  {
    "date": "2024-08-15",
    "close": 535.9085083008,
    "volume": 13482100
  },
  {
    "date": "2024-08-16",
    "close": 526.024597168,
    "volume": 14776700
  },
  {
    "date": "2024-08-19",
    "close": 527.8797607422,
    "volume": 9879700
  },
  {
    "date": "2024-08-20",
    "close": 525.3364257812,
    "volume": 7944400
  },
  {
    "date": "2024-08-21",
    "close": 533.744140625,
    "volume": 13423300
  },
  {
    "date": "2024-08-22",
    "close": 530.5227050781,
    "volume": 15708300
  },
  {
    "date": "2024-08-23",
    "close": 526.6031494141,
    "volume": 11323900
  },
  {
    "date": "2024-08-26",
    "close": 519.7413330078,
    "volume": 9584000
  },
  {
    "date": "2024-08-27",
    "close": 517.7266235352,
    "volume": 6282700
  },
  {
    "date": "2024-08-28",
    "close": 515.4128417969,
    "volume": 9106100
  },
  {
    "date": "2024-08-29",
    "close": 516.8489990234,
    "volume": 8317400
  },
  {
    "date": "2024-08-30",
    "close": 519.9307861328,
    "volume": 9157500
  },
  {
    "date": "2024-09-03",
    "close": 510.4060974121,
    "volume": 12459100
  },
  {
    "date": "2024-09-04",
    "close": 511.3834533691,
    "volume": 8335200
  },
  {
    "date": "2024-09-05",
    "close": 515.4926147461,
    "volume": 8640900
  },
  {
    "date": "2024-09-06",
    "close": 498.946472168,
    "volume": 14744500
  },
  {
    "date": "2024-09-09",
    "close": 503.4545288086,
    "volume": 11047800
  },
  {
    "date": "2024-09-10",
    "close": 503.4545288086,
    "volume": 9899000
  },
  {
    "date": "2024-09-11",
    "close": 510.4758605957,
    "volume": 10782500
  },
  {
    "date": "2024-09-12",
    "close": 524.2094726562,
    "volume": 11993300
  },
  {
    "date": "2024-09-13",
    "close": 523.2320556641,
    "volume": 10321400
  },
  {
    "date": "2024-09-16",
    "close": 532.3765869141,
    "volume": 9527600
  },
  {
    "date": "2024-09-17",
    "close": 535.4114379883,
    "volume": 11690800
  },
  {
    "date": "2024-09-18",
    "close": 537.0386352539,
    "volume": 10323500
  },
  {
    "date": "2024-09-19",
    "close": 558.1527709961,
    "volume": 15647000
  },
  {
    "date": "2024-09-20",
    "close": 560.3989257812,
    "volume": 22066800
  },
  {
    "date": "2024-09-23",
    "close": 563.4537963867,
    "volume": 12830700
  },
  {
    "date": "2024-09-24",
    "close": 562.3756713867,
    "volume": 12993000
  },
  {
    "date": "2024-09-25",
    "close": 567.3471679688,
    "volume": 16543400
  },
  {
    "date": "2024-09-26",
    "close": 566.8780517578,
    "volume": 14400800
  },
  {
    "date": "2024-09-27",
    "close": 566.3988037109,
    "volume": 9398400
  },
  {
    "date": "2024-09-30",
    "close": 571.4702148438,
    "volume": 12792300
  },
  {
    "date": "2024-10-01",
    "close": 575.493347168,
    "volume": 15259300
  },
  {
    "date": "2024-10-02",
    "close": 571.8395996094,
    "volume": 6524700
  },
  {
    "date": "2024-10-03",
    "close": 581.7827148438,
    "volume": 11581000
  },
  {
    "date": "2024-10-04",
    "close": 594.9304199219,
    "volume": 14169500
  },
  {
    "date": "2024-10-07",
    "close": 583.7893066406,
    "volume": 12014200
  },
  {
    "date": "2024-10-08",
    "close": 591.885559082,
    "volume": 7857400
  },
  {
    "date": "2024-10-09",
    "close": 589.5095825195,
    "volume": 9529700
  },
  {
    "date": "2024-10-10",
    "close": 582.8408813477,
    "volume": 7740400
  },
  {
    "date": "2024-10-11",
    "close": 588.9505615234,
    "volume": 8587100
  },
  {
    "date": "2024-10-14",
    "close": 589.4196777344,
    "volume": 8252000
  },
  {
    "date": "2024-10-15",
    "close": 585.2767944336,
    "volume": 9564200
  },
  {
    "date": "2024-10-16",
    "close": 575.8128051758,
    "volume": 11268400
  },
  {
    "date": "2024-10-17",
    "close": 575.9526367188,
    "volume": 8701200
  },
  {
    "date": "2024-10-18",
    "close": 575.493347168,
    "volume": 7694300
  },
  {
    "date": "2024-10-21",
    "close": 574.185546875,
    "volume": 8171900
  },
  {
    "date": "2024-10-22",
    "close": 581.0240478516,
    "volume": 8544500
  },
  {
    "date": "2024-10-23",
    "close": 562.7349853516,
    "volume": 14248400
  },
  {
    "date": "2024-10-24",
    "close": 566.8181152344,
    "volume": 7184700
  },
  {
    "date": "2024-10-25",
    "close": 572.2788085938,
    "volume": 11337900
  },
  {
    "date": "2024-10-28",
    "close": 577.180480957,
    "volume": 10925100
  },
  {
    "date": "2024-10-29",
    "close": 592.2749633789,
    "volume": 13019100
  },
  {
    "date": "2024-10-30",
    "close": 590.7973632812,
    "volume": 26864900
  },
  {
    "date": "2024-10-31",
    "close": 566.6184692383,
    "volume": 26838400
  },
  {
    "date": "2024-11-01",
    "close": 566.1991577148,
    "volume": 15303200
  },
  {
    "date": "2024-11-04",
    "close": 559.7301025391,
    "volume": 12064600
  },
  {
    "date": "2024-11-05",
    "close": 571.4602050781,
    "volume": 9775400
  },
  {
    "date": "2024-11-06",
    "close": 571.080871582,
    "volume": 18305400
  },
  {
    "date": "2024-11-07",
    "close": 590.6976318359,
    "volume": 14653700
  },
  {
    "date": "2024-11-08",
    "close": 588.3416137695,
    "volume": 9415700
  },
  {
    "date": "2024-11-11",
    "close": 582.1820068359,
    "volume": 10209100
  },
  {
    "date": "2024-11-12",
    "close": 583.8292236328,
    "volume": 16287700
  },
  {
    "date": "2024-11-13",
    "close": 579.0173950195,
    "volume": 10757600
  },
  {
    "date": "2024-11-14",
    "close": 576.1821899414,
    "volume": 11053700
  },
  {
    "date": "2024-11-15",
    "close": 553.1412963867,
    "volume": 17712900
  },
  {
    "date": "2024-11-18",
    "close": 553.4608154297,
    "volume": 14346700
  },
  {
    "date": "2024-11-19",
    "close": 560.139465332,
    "volume": 9522400
  },
  {
    "date": "2024-11-20",
    "close": 564.5619506836,
    "volume": 9797300
  },
  {
    "date": "2024-11-21",
    "close": 562.1360473633,
    "volume": 11154700
  },
  {
    "date": "2024-11-22",
    "close": 558.1928100586,
    "volume": 9164000
  },
  {
    "date": "2024-11-25",
    "close": 564.1526489258,
    "volume": 13599800
  },
  {
    "date": "2024-11-26",
    "close": 572.5682983398,
    "volume": 10356600
  },
  {
    "date": "2024-11-27",
    "close": 568.2357177734,
    "volume": 7200200
  },
  {
    "date": "2024-11-29",
    "close": 573.3470458984,
    "volume": 7130500
  },
  {
    "date": "2024-12-02",
    "close": 591.8256835938,
    "volume": 12522400
  },
  {
    "date": "2024-12-03",
    "close": 612.6104125977,
    "volume": 14907200
  },
  {
    "date": "2024-12-04",
    "close": 612.7401733398,
    "volume": 14697000
  },
  {
    "date": "2024-12-05",
    "close": 607.8983764648,
    "volume": 8081200
  },
  {
    "date": "2024-12-06",
    "close": 622.7132568359,
    "volume": 16935500
  },
  {
    "date": "2024-12-09",
    "close": 612.5305175781,
    "volume": 11426000
  },
  {
    "date": "2024-12-10",
    "close": 618.2708129883,
    "volume": 10938900
  },
  {
    "date": "2024-12-11",
    "close": 631.6080932617,
    "volume": 10837200
  },
  {
    "date": "2024-12-12",
    "close": 629.7213134766,
    "volume": 7474700
  },
  {
    "date": "2024-12-13",
    "close": 619.2990112305,
    "volume": 8453300
  },
  {
    "date": "2024-12-16",
    "close": 623.6851196289,
    "volume": 10885600
  },
  {
    "date": "2024-12-17",
    "close": 618.8894042969,
    "volume": 12897800
  },
  {
    "date": "2024-12-18",
    "close": 596.6591796875,
    "volume": 17075500
  },
  {
    "date": "2024-12-19",
    "close": 595.0405883789,
    "volume": 14958100
  },
  {
    "date": "2024-12-20",
    "close": 584.7297973633,
    "volume": 48989400
  },
  {
    "date": "2024-12-23",
    "close": 599.3167724609,
    "volume": 10205800
  },
  {
    "date": "2024-12-24",
    "close": 607.209777832,
    "volume": 4726100
  },
  {
    "date": "2024-12-26",
    "close": 602.813659668,
    "volume": 6081400
  },
  {
    "date": "2024-12-27",
    "close": 599.2768554688,
    "volume": 8084200
  },
  {
    "date": "2024-12-30",
    "close": 590.7144165039,
    "volume": 7025900
  },
  {
    "date": "2024-12-31",
    "close": 584.9895629883,
    "volume": 6019500
  },
  {
    "date": "2025-01-02",
    "close": 598.7073364258,
    "volume": 12682300
  },
  {
    "date": "2025-01-03",
    "close": 604.0925292969,
    "volume": 11436800
  },
  {
    "date": "2025-01-06",
    "close": 629.639831543,
    "volume": 14560800
  },
  {
    "date": "2025-01-07",
    "close": 617.3407592773,
    "volume": 12071500
  },
  {
    "date": "2025-01-08",
    "close": 610.1771240234,
    "volume": 10085800
  },
  {
    "date": "2025-01-10",
    "close": 615.3125610352,
    "volume": 19256600
  },
  {
    "date": "2025-01-13",
    "close": 607.7893066406,
    "volume": 10785000
  },
  {
    "date": "2025-01-14",
    "close": 593.7218017578,
    "volume": 13598000
  },
  {
    "date": "2025-01-15",
    "close": 616.571472168,
    "volume": 15524300
  },
  {
    "date": "2025-01-16",
    "close": 610.7565917969,
    "volume": 8355300
  },
  {
    "date": "2025-01-17",
    "close": 612.2253417969,
    "volume": 17280600
  },
  {
    "date": "2025-01-21",
    "close": 615.9120483398,
    "volume": 11674000
  },
  {
    "date": "2025-01-22",
    "close": 622.9458007812,
    "volume": 12274000
  },
  {
    "date": "2025-01-23",
    "close": 635.8842773438,
    "volume": 9910200
  },
  {
    "date": "2025-01-24",
    "close": 646.9144287109,
    "volume": 19065300
  },
  {
    "date": "2025-01-27",
    "close": 659.2934570312,
    "volume": 28399200
  },
  {
    "date": "2025-01-28",
    "close": 673.7305908203,
    "volume": 20950100
  },
  {
    "date": "2025-01-29",
    "close": 675.888671875,
    "volume": 21377800
  },
  {
    "date": "2025-01-30",
    "close": 686.3893432617,
    "volume": 29322900
  },
  {
    "date": "2025-01-31",
    "close": 688.5673828125,
    "volume": 19331700
  },
  {
    "date": "2025-02-03",
    "close": 696.8400878906,
    "volume": 21415700
  },
  {
    "date": "2025-02-04",
    "close": 703.5640869141,
    "volume": 13826300
  },
  {
    "date": "2025-02-05",
    "close": 704.2434692383,
    "volume": 17778200
  },
  {
    "date": "2025-02-06",
    "close": 711.3571166992,
    "volume": 13080700
  },
  {
    "date": "2025-02-07",
    "close": 713.8848876953,
    "volume": 16427100
  },
  {
    "date": "2025-02-10",
    "close": 716.7623291016,
    "volume": 12904300
  },
  {
    "date": "2025-02-11",
    "close": 719.16015625,
    "volume": 12998000
  },
  {
    "date": "2025-02-12",
    "close": 724.7352294922,
    "volume": 12016500
  },
  {
    "date": "2025-02-13",
    "close": 727.9124145508,
    "volume": 12569100
  },
  {
    "date": "2025-02-14",
    "close": 736.0151977539,
    "volume": 16901200
  },
  {
    "date": "2025-02-18",
    "close": 715.733215332,
    "volume": 21938700
  },
  {
    "date": "2025-02-19",
    "close": 703.1444702148,
    "volume": 17535500
  },
  {
    "date": "2025-02-20",
    "close": 694.2224121094,
    "volume": 12587400
  },
  {
    "date": "2025-02-21",
    "close": 682.9423828125,
    "volume": 15660400
  },
  {
    "date": "2025-02-24",
    "close": 667.5361328125,
    "volume": 15677000
  },
  {
    "date": "2025-02-25",
    "close": 656.9155883789,
    "volume": 20579700
  },
  {
    "date": "2025-02-26",
    "close": 673.1011962891,
    "volume": 14488700
  },
  {
    "date": "2025-02-27",
    "close": 657.6549072266,
    "volume": 12500000
  },
  {
    "date": "2025-02-28",
    "close": 667.6060791016,
    "volume": 17534200
  },
  {
    "date": "2025-03-03",
    "close": 654.4677124023,
    "volume": 10843800
  },
  {
    "date": "2025-03-04",
    "close": 639.4310913086,
    "volume": 21495200
  },
  {
    "date": "2025-03-05",
    "close": 655.8864746094,
    "volume": 13770000
  },
  {
    "date": "2025-03-06",
    "close": 627.3718261719,
    "volume": 13446500
  },
  {
    "date": "2025-03-07",
    "close": 625.1038208008,
    "volume": 21375700
  },
  {
    "date": "2025-03-10",
    "close": 597.4584350586,
    "volume": 21999900
  },
  {
    "date": "2025-03-11",
    "close": 605.1716308594,
    "volume": 17401500
  },
  {
    "date": "2025-03-12",
    "close": 619.0092773438,
    "volume": 15747000
  },
  {
    "date": "2025-03-13",
    "close": 590.1149902344,
    "volume": 16480300
  },
  {
    "date": "2025-03-14",
    "close": 607.5999755859,
    "volume": 12364500
  },
  {
    "date": "2025-03-17",
    "close": 604.9000244141,
    "volume": 15473900
  },
  {
    "date": "2025-03-18",
    "close": 582.3599853516,
    "volume": 20297700
  },
  {
    "date": "2025-03-19",
    "close": 584.0599975586,
    "volume": 20497100
  }
]
